di_easy-1.1.0.dist-info/licenses/LICENSE
easy_di/__init__.py
easy_di/base_injector.py
easy_di/exceptions.py
easy_di/group_injector.py
di_easy-1.1.0.dist-info/METADATA
di_easy-1.1.0.dist-info/WHEEL
di_easy-1.1.0.dist-info/top_level.txt
di_easy-1.1.0.dist-info/RECORD
