Metadata-Version: 2.4
Name: di-easy
Version: 1.1.0
Summary: Library for easy dependency injection
Author-email: David Lishchyshen <microdaika1@gmail.com>
Project-URL: Homepage, https://github.com/AsfhtgkDavid/easy-di
Keywords: easy,lightweight,di,dependency,injection,easy-di
Classifier: Development Status :: 5 - Production/Stable
Classifier: Intended Audience :: Developers
Classifier: License :: OSI Approved :: MIT License
Classifier: Programming Language :: Python
Classifier: Programming Language :: Python :: 3.6
Classifier: Programming Language :: Python :: 3.7
Classifier: Programming Language :: Python :: 3.8
Classifier: Programming Language :: Python :: 3.9
Classifier: Programming Language :: Python :: 3.10
Classifier: Programming Language :: Python :: 3.11
Classifier: Programming Language :: Python :: 3.12
Classifier: Programming Language :: Python :: 3.13
Classifier: Programming Language :: Python :: 3.14
Classifier: Topic :: Software Development :: Libraries
Classifier: Topic :: Software Development :: Libraries :: Python Modules
Classifier: Topic :: Software Development :: Testing
Classifier: Typing :: Typed
Requires-Python: >=3.6
License-File: LICENSE
Requires-Dist: typing-extensions>=4.0.0; python_full_version < "3.10"
Dynamic: license-file
